monadc/__init__.py
monadc/decorators.py
monadc/either/__init__.py
monadc/either/either.py
monadc/either/left.py
monadc/either/right.py
monadc/option/__init__.py
monadc/option/nil.py
monadc/option/option.py
monadc/option/some.py
monadc/result/__init__.py
monadc/result/err.py
monadc/result/ok.py
monadc/result/result.py
monadc/try_/__init__.py
monadc/try_/failure.py
monadc/try_/success.py
monadc/try_/try_.py
monadc-0.1.0.dist-info/METADATA
monadc-0.1.0.dist-info/WHEEL
monadc-0.1.0.dist-info/licenses/LICENSE
monadc-0.1.0.dist-info/RECORD
