Metadata-Version: 2.4
Name: monadc
Version: 0.1.0
Summary: Comprehensive functional programming monads for Python - Option, Either, Try, Result types with full MyPy support
Project-URL: Homepage, https://github.com/carlyou/monadc
Project-URL: Repository, https://github.com/carlyou/monadc.git
Project-URL: Issues, https://github.com/carlyou/monadc/issues
Author: Carl You
License: MIT
License-File: LICENSE
Keywords: either,functional,monads,option,programming,result,rust,scala,try
Classifier: Development Status :: 4 - Beta
Classifier: Intended Audience :: Developers
Classifier: License :: OSI Approved :: MIT License
Classifier: Programming Language :: Python :: 3
Classifier: Programming Language :: Python :: 3.10
Classifier: Programming Language :: Python :: 3.11
Classifier: Programming Language :: Python :: 3.12
Classifier: Topic :: Software Development :: Libraries :: Python Modules
Classifier: Typing :: Typed
Requires-Python: >=3.10
Provides-Extra: dev
Requires-Dist: pytest-cov>=4.0.0; extra == 'dev'
Requires-Dist: pytest>=7.0.0; extra == 'dev'
